jupyter_drives_browser/__init__.py
jupyter_drives_browser/_version.py
jupyter_drives_browser-0.1.0a0.data/data/share/jupyter/labextensions/jupyter-drives-browser/package.json
jupyter_drives_browser-0.1.0a0.data/data/share/jupyter/labextensions/jupyter-drives-browser/schemas/jupyter-drives-browser/file-browser-toolbar.json
jupyter_drives_browser-0.1.0a0.data/data/share/jupyter/labextensions/jupyter-drives-browser/schemas/jupyter-drives-browser/package.json.orig
jupyter_drives_browser-0.1.0a0.data/data/share/jupyter/labextensions/jupyter-drives-browser/static/52.16aa97a20862b16c93c9.js
jupyter_drives_browser-0.1.0a0.data/data/share/jupyter/labextensions/jupyter-drives-browser/static/728.4a8ed3f4f14a971aa742.js
jupyter_drives_browser-0.1.0a0.data/data/share/jupyter/labextensions/jupyter-drives-browser/static/732.a5ac8fc56cc8b244d7e0.js
jupyter_drives_browser-0.1.0a0.data/data/share/jupyter/labextensions/jupyter-drives-browser/static/75.541c77ec7ebfeeee5c8c.js
jupyter_drives_browser-0.1.0a0.data/data/share/jupyter/labextensions/jupyter-drives-browser/static/75.541c77ec7ebfeeee5c8c.js.LICENSE.txt
jupyter_drives_browser-0.1.0a0.data/data/share/jupyter/labextensions/jupyter-drives-browser/static/935.b61aac0b57155621471f.js
jupyter_drives_browser-0.1.0a0.data/data/share/jupyter/labextensions/jupyter-drives-browser/static/remoteEntry.12eaad870a408f936581.js
jupyter_drives_browser-0.1.0a0.data/data/share/jupyter/labextensions/jupyter-drives-browser/static/style.js
jupyter_drives_browser-0.1.0a0.data/data/share/jupyter/labextensions/jupyter-drives-browser/static/third-party-licenses.json
jupyter_drives_browser-0.1.0a0.data/data/share/jupyter/labextensions/jupyter-drives-browser/install.json
jupyter_drives_browser-0.1.0a0.dist-info/METADATA
jupyter_drives_browser-0.1.0a0.dist-info/WHEEL
jupyter_drives_browser-0.1.0a0.dist-info/licenses/LICENSE
jupyter_drives_browser-0.1.0a0.dist-info/RECORD
